text_formatter/__init__.py
text_formatter/justify.py
text_formatter-1.0.0.dev4.dist-info/AUTHORS.txt
text_formatter-1.0.0.dev4.dist-info/LICENSE.txt
text_formatter-1.0.0.dev4.dist-info/METADATA
text_formatter-1.0.0.dev4.dist-info/WHEEL
text_formatter-1.0.0.dev4.dist-info/top_level.txt
text_formatter-1.0.0.dev4.dist-info/RECORD
